{
  "config": {
    "model_type": "rnn",
    "input_size": 40,
    "hidden_size": 256,
    "num_layers": 3,
    "bidirectional": false,
    "dropout": 0.1,
    "optimizer": "adam",
    "learning_rate": 0.001,
    "weight_decay": 1e-05,
    "epochs": 30,
    "scheduler": "step",
    "scheduler_step_size": 10,
    "scheduler_gamma": 0.5
  },
  "history": {
    "train_loss": [
      2.3868959562554544,
      2.374809146586044,
      2.373048817913835,
      2.370257099689041,
      2.3708713614479615,
      2.36876705865175
    ],
    "train_acc": [
      0.18801795580110497,
      0.1980749309392265,
      0.19332700276243095,
      0.1979886049723757,
      0.1968232044198895,
      0.1980749309392265
    ],
    "val_loss": [
      2.353110575372482,
      2.3532240988489486,
      2.3578291997447662,
      2.3532579170921064,
      2.3554500967625023,
      2.3696316808545417
    ],
    "val_acc": [
      0.1999379074821484,
      0.1999379074821484,
      0.1999379074821484,
      0.1999379074821484,
      0.1999379074821484,
      0.1999379074821484
    ]
  },
  "best_val_acc": 0.1999379074821484,
  "test_acc": 0.19981296758104738,
  "confusion_matrix": [
    [
      0,
      0,
      0,
      0,
      0,
      0,
      0,
      0,
      253,
      0,
      0
    ],
    [
      0,
      0,
      0,
      0,
      0,
      0,
      0,
      0,
      251,
      0,
      0
    ],
    [
      0,
      0,
      0,
      0,
      0,
      0,
      0,
      0,
      267,
      0,
      0
    ],
    [
      0,
      0,
      0,
      0,
      0,
      0,
      0,
      0,
      252,
      0,
      0
    ],
    [
      0,
      0,
      0,
      0,
      0,
      0,
      0,
      0,
      262,
      0,
      0
    ],
    [
      0,
      0,
      0,
      0,
      0,
      0,
      0,
      0,
      246,
      0,
      0
    ],
    [
      0,
      0,
      0,
      0,
      0,
      0,
      0,
      0,
      259,
      0,
      0
    ],
    [
      0,
      0,
      0,
      0,
      0,
      0,
      0,
      0,
      249,
      0,
      0
    ],
    [
      0,
      0,
      0,
      0,
      0,
      0,
      0,
      0,
      641,
      0,
      0
    ],
    [
      0,
      0,
      0,
      0,
      0,
      0,
      0,
      0,
      272,
      0,
      0
    ],
    [
      0,
      0,
      0,
      0,
      0,
      0,
      0,
      0,
      256,
      0,
      0
    ]
  ],
  "id2label": {
    "0": "down",
    "1": "go",
    "2": "left",
    "3": "no",
    "4": "off",
    "5": "on",
    "6": "right",
    "7": "stop",
    "8": "unknown",
    "9": "up",
    "10": "yes"
  }
}